abaqus_parse/__init__.py
abaqus_parse/_version.py
abaqus_parse/compute_forming_limit_curve.py
abaqus_parse/generate_MK_mesh.py
abaqus_parse/parts.py
abaqus_parse/plots.py
abaqus_parse/readers.py
abaqus_parse/save_model_response.py
abaqus_parse/steps.py
abaqus_parse/utils.py
abaqus_parse/write_MK_mesh.py
abaqus_parse/writers.py
abaqus_parse/yield_functions.py
abaqus_parse/materials/__init__.py
abaqus_parse/materials/euromat_A.py
abaqus_parse-0.1.3.dist-info/LICENSE
abaqus_parse-0.1.3.dist-info/METADATA
abaqus_parse-0.1.3.dist-info/WHEEL
abaqus_parse-0.1.3.dist-info/top_level.txt
abaqus_parse-0.1.3.dist-info/RECORD
