Metadata-Version: 2.1
Name: abaqus-parse
Version: 0.1.3
Summary: Abaqus input and output file readers and writers.
Home-page: UNKNOWN
Author: Maria S. Yankova
Author-email: maria.yankova@manchester.ac.uk
License: MIT license
Project-URL: GitHub, https://github.com/maria-yankova/abaqus-parse
Keywords: abaqus,fea,materials-science
Platform: UNKNOWN
Classifier: Development Status :: 4 - Beta
Classifier: Intended Audience :: Science/Research
Classifier: Topic :: Scientific/Engineering
Classifier: Operating System :: OS Independent
Classifier: License :: OSI Approved :: MIT License
Classifier: Natural Language :: English
Classifier: Programming Language :: Python :: 3
Classifier: Programming Language :: Python :: 3.6
Classifier: Programming Language :: Python :: 3.7
Classifier: Programming Language :: Python :: 3.8
Requires-Python: >=3.6
Requires-Dist: numpy
Requires-Dist: calfem-python
Requires-Dist: fracture-fea-laf (==0.1.1)
Requires-Dist: plotly
